tsquery/__init__.py
tsquery/__main__.py
tsquery/cli.py
tsquery/parser_registry.py
tsquery/xdg.py
tsquery-0.1.1.dist-info/LICENSE.txt
tsquery-0.1.1.dist-info/METADATA
tsquery-0.1.1.dist-info/WHEEL
tsquery-0.1.1.dist-info/entry_points.txt
tsquery-0.1.1.dist-info/top_level.txt
tsquery-0.1.1.dist-info/RECORD
