Metadata-Version: 2.1
Name: tsquery
Version: 0.1.1
Summary: Run Tree Sitter queries from the command line
Home-page: https://sr.ht/~wintershadows/tsquery
Author: Greg Werbin
Author-email: software@me.gregwerbin.com
License: GPL-3.0-or-later
Platform: UNKNOWN
Requires-Python: >=3.9
Requires-Dist: attrs (>=20)
Requires-Dist: click (>=7)
Requires-Dist: tree-sitter (>=0.2.0)
